MANIFEST.in
setup.py
simplewebshell/__init__.py
simplewebshell/index.html
simplewebshell/termlib.js
simplewebshell.egg-info/PKG-INFO
simplewebshell.egg-info/SOURCES.txt
simplewebshell.egg-info/dependency_links.txt
simplewebshell.egg-info/entry_points.txt
simplewebshell.egg-info/top_level.txt